{
    "url": "https://www.presidency.ucsb.edu/documents/executive-order-civil-service-amendment-classification-0",
    "doc": "executive-order-civil-service-amendment-classification-0",
    "president": "Grover Cleveland",
    "president_byline": "24th President of the United States: 1893 - 1897",
    "title": "Executive Order-Civil Service: Amendment of Classification",
    "date": "November 02, 1894",
    "content": [
        "In pursuance of the authority contained in the third paragraph of section 6 of the act entitled \"An act to regulate and improve the civil service of the United States,\" approved January 16, 1883, the Postmaster-General is hereby directed to amend the classification of the Post-Office Department so as to include among the classes covered thereby clerks to post-office inspectors.",
        "[NAME], November 2, 1894.",
        "[NAME]."
    ],
    "citation": "Grover Cleveland, Executive Order-Civil Service: Amendment of Classification Online by Gerhard Peters and John T. Woolley, The American Presidency Project https://www.presidency.ucsb.edu/node/206455"
}