{
    "initial_scores": {
        "joy": 1,
        "sadness": 1,
        "fear": 1,
        "disgust": 1,
        "surprise": 1
    },
    "critique": "The document is a formal announcement of appointments. It does not express strong emotions. The language is formal and legalistic. Therefore, I would expect low scores for all emotions. The initial scores are all 1.",
    "revised_scores": {
        "joy": 1,
        "sadness": 1,
        "fear": 1,
        "disgust": 1,
        "surprise": 1
    }
}