{
    "initial_scores": {
        "joy": 1,
        "sadness": 1,
        "fear": 1,
        "disgust": 1,
        "surprise": 2
    },
    "critique": "The document is a formal executive order. It primarily conveys a sense of necessity and adjustment, rather than strong emotions. The tone is neutral and factual. Therefore, most emotions should be scored low. There might be a slight sense of surprise that the abolition date needs to be deferred, but it's minimal.",
    "revised_scores": {
        "joy": 1,
        "sadness": 1,
        "fear": 1,
        "disgust": 1,
        "surprise": 2
    }
}