{
    "initial_scores": {
        "joy": 1,
        "sadness": 1,
        "fear": 1,
        "disgust": 1,
        "surprise": 1
    },
    "critique": "The document is a formal executive order regarding the award of life-saving medals. It outlines the regulations and procedures for applying for and awarding these medals. The language is legalistic and procedural, with no indication of emotions such as joy, sadness, anger, fear, disgust, or surprise. The document focuses on establishing clear guidelines and processes. Therefore, all emotions should be scored as 1.",
    "revised_scores": {
        "joy": 1,
        "sadness": 1,
        "fear": 1,
        "disgust": 1,
        "surprise": 1
    }
}