{
    "initial_scores": {
        "joy": 1,
        "sadness": 1,
        "fear": 5,
        "disgust": 1,
        "surprise": 1
    },
    "critique": "The executive order seems to want to convey a sense of urgency and seriousness, but not necessarily fear or disgust. It's more about preparedness and coordination. Surprise is not really an emotion sought here, and joy is inappropriate. Sadness is also not relevant.",
    "revised_scores": {
        "joy": 1,
        "sadness": 1,
        "fear": 6,
        "disgust": 1,
        "surprise": 1
    }
}