{
    "initial_scores": {
        "joy": 2,
        "sadness": 1,
        "fear": 2,
        "disgust": 3,
        "surprise": 2
    },
    "critique": "The document is a formal executive order. It outlines policy changes regarding federal employees in confidential, policy-determining, policy-making, or policy-advocating roles. The language is formal and legalistic. There is no explicit expression of emotion. However, the order implies a sense of dissatisfaction with the current performance management system and a desire for greater efficiency and accountability. This could be interpreted as a mild form of disgust or frustration. The order also conveys a sense of determination to improve the effectiveness of the executive branch. Given the nature of the document, the expected emotional response from the public is likely to be muted. Some may feel surprise or fear depending on their political views and how they perceive the potential impact of the order on federal employees. Others may feel joy if they believe it will lead to a more efficient government. However, overall, the emotional intensity is likely to be low.",
    "revised_scores": {
        "joy": 2,
        "sadness": 1,
        "fear": 2,
        "disgust": 3,
        "surprise": 2
    }
}