{
    "initial_scores": {
        "joy": 3,
        "sadness": 2,
        "fear": 1,
        "disgust": 1,
        "surprise": 1
    },
    "critique": "The document is a formal executive order regarding the phasing out of substances that deplete the ozone layer. It expresses a sense of responsibility and determination to address an environmental issue. There is a mild sense of optimism due to the focus on innovative safe alternatives. There is no indication of emotions such as fear, disgust, or surprise. The document is largely neutral in tone, as expected for a formal government document.",
    "revised_scores": {
        "joy": 3,
        "sadness": 2,
        "fear": 1,
        "disgust": 1,
        "surprise": 1
    }
}