{
    "initial_scores": {
        "joy": 6,
        "sadness": 2,
        "fear": 4,
        "disgust": 3,
        "surprise": 3
    },
    "critique": "The document primarily conveys a sense of purpose and determination to improve the healthcare system. The President aims to instill confidence and hope in the American public by addressing issues such as price transparency, quality of care, and surprise billing. While there's no explicit expression of joy, the intended outcome of these policies is to bring relief and satisfaction to patients. There's a subtle undercurrent of concern regarding the current state of the healthcare system, particularly the lack of transparency and the prevalence of surprise billing, which could evoke a sense of unease or fear. However, the overall tone is optimistic and proactive, focusing on solutions and improvements. Disgust is not explicitly conveyed, but there might be an implicit disapproval of the 'opaque pricing structures' and 'harmful practices' like surprise billing. Surprise is not a primary emotion conveyed, but the document does address unexpected medical bills, which could indirectly relate to surprise. The document does not convey anger or sadness.",
    "revised_scores": {
        "joy": 6,
        "sadness": 2,
        "fear": 4,
        "disgust": 3,
        "surprise": 3
    }
}