{
    "initial_scores": {
        "joy": 7,
        "sadness": 3,
        "fear": 1,
        "disgust": 1,
        "surprise": 5
    },
    "critique": "The document expresses optimism and a call to national unity and celebration. The primary emotion conveyed is joy, with secondary emotions of surprise at the possibilities of the future and perhaps a touch of sadness when reflecting on the past. There's no indication of anger, fear, or disgust.",
    "revised_scores": {
        "joy": 8,
        "sadness": 2,
        "fear": 1,
        "disgust": 1,
        "surprise": 4
    }
}