{
    "initial_scores": {
        "joy": 1,
        "sadness": 2,
        "fear": 3,
        "disgust": 1,
        "surprise": 2
    },
    "critique": "The document is a formal executive order addressing a labor dispute. It primarily conveys a sense of urgency and importance in resolving the issue to maintain essential transportation services. There's a hint of concern about the potential disruption to interstate commerce. However, given the formal nature, strong emotions are unlikely to be explicitly expressed. The initial scores reflect this baseline assessment.",
    "revised_scores": {
        "joy": 1,
        "sadness": 2,
        "fear": 3,
        "disgust": 1,
        "surprise": 2
    }
}