{
    "initial_scores": {
        "joy": 1,
        "sadness": 8,
        "fear": 1,
        "disgust": 1,
        "surprise": 3
    },
    "critique": "The executive order primarily aims to evoke sadness and perhaps a touch of sympathy/surprise. The order describes a widow and her daughters left without support due to the husband's suicide, clearly intending to elicit sadness. There might be a slight surprise at the unusual nature of the order, but sadness is the dominant emotion. There's no indication of joy, anger, fear, or disgust.",
    "revised_scores": {
        "joy": 1,
        "sadness": 9,
        "fear": 1,
        "disgust": 1,
        "surprise": 2
    }
}