{
    "initial_scores": {
        "joy": 4,
        "sadness": 1,
        "fear": 1,
        "disgust": 1,
        "surprise": 3
    },
    "critique": "Initial assessment: This document is a formal executive order establishing a Recreation Advisory Council. The primary emotions conveyed are related to the importance of outdoor recreation and the need for coordinated efforts to manage related resources. There is a sense of optimism and purpose, but the overall tone is formal and measured. The initial scores reflect this, with low scores for negative emotions and moderate scores for joy and surprise (related to the establishment of the council). Revised assessment: Upon further review, the document's emphasis on conservation, wise use of resources, and making recreation accessible to all suggests a stronger sense of joy and purpose than initially assessed. The establishment of the council and the focus on inter-agency coordination also imply a degree of surprise or novelty. The revised scores reflect these adjustments, with slightly increased scores for joy and surprise.",
    "revised_scores": {
        "joy": 5,
        "sadness": 1,
        "fear": 1,
        "disgust": 1,
        "surprise": 4
    }
}