{
    "initial_scores": {
        "joy": 1,
        "sadness": 1,
        "fear": 1,
        "disgust": 1,
        "surprise": 1
    },
    "critique": "The document is a formal executive order regarding actions against the Government of Iraq. It is primarily a legal and administrative document. Therefore, the primary emotions conveyed would be related to the seriousness and urgency of the situation, but not in a strong way. There is no strong indication of joy, sadness, fear, disgust, or surprise. The document aims to convey authority and decisiveness.",
    "revised_scores": {
        "joy": 1,
        "sadness": 1,
        "fear": 1,
        "disgust": 1,
        "surprise": 1
    }
}