{
    "initial_scores": {
        "joy": 3,
        "sadness": 2,
        "fear": 1,
        "disgust": 1,
        "surprise": 1
    },
    "critique": "The document is a formal executive order establishing a commission for the International Year of the Child. The language is legal and procedural, with no explicit emotional expression. However, the underlying intent to improve the well-being of children could be interpreted as conveying a sense of joy and perhaps a response to sadness or need. Given the formal nature, the emotional intensity is likely to be perceived as low by the public.",
    "revised_scores": {
        "joy": 3,
        "sadness": 2,
        "fear": 1,
        "disgust": 1,
        "surprise": 1
    }
}