{
    "initial_scores": {
        "joy": 5,
        "sadness": 3,
        "fear": 2,
        "disgust": 1,
        "surprise": 4
    },
    "critique": "The executive order seems to aim for a sense of order and progress, potentially instilling a sense of joy and surprise that the government is working efficiently. However, it could also cause sadness and fear for those negatively affected by the order. Disgust is unlikely to be a primary emotion.",
    "revised_scores": {
        "joy": 5,
        "sadness": 3,
        "fear": 2,
        "disgust": 1,
        "surprise": 4
    }
}