{
    "initial_scores": {
        "joy": 4,
        "sadness": 1,
        "fear": 1,
        "disgust": 1,
        "surprise": 1
    },
    "critique": "The document is a formal executive order. It expresses a desire to promote economic and national security, stimulate economic growth, create jobs, and protect American workers. There is a sense of determination and resolve in the language, but it is primarily a policy document. Therefore, the emotions conveyed are relatively mild. Joy is present due to the focus on economic growth and job creation. Sadness is minimal. There is no anger, fear, disgust, or surprise.",
    "revised_scores": {
        "joy": 4,
        "sadness": 1,
        "fear": 1,
        "disgust": 1,
        "surprise": 1
    }
}