{
    "initial_scores": {
        "joy": 2,
        "sadness": 1,
        "fear": 1,
        "disgust": 1,
        "surprise": 2
    },
    "critique": "The executive order seems to be a technical document about civil service rules. It is unlikely to evoke strong emotions. The order might bring a slight sense of joy to those who benefit from it, and perhaps a hint of surprise at the specific nature of the amendment. However, the overall emotional impact is minimal.",
    "revised_scores": {
        "joy": 2,
        "sadness": 1,
        "fear": 1,
        "disgust": 1,
        "surprise": 2
    }
}