{
    "initial_scores": {
        "joy": 1,
        "sadness": 1,
        "fear": 1,
        "disgust": 1,
        "surprise": 1
    },
    "critique": "The document is a formal executive order regarding the Panama Canal Zone. It primarily delegates authority and outlines regulations. There is no strong emotional sentiment conveyed. The language is legal and administrative, aiming for clarity and precision rather than evoking emotions. Therefore, all emotions should be scored low.",
    "revised_scores": {
        "joy": 1,
        "sadness": 1,
        "fear": 1,
        "disgust": 1,
        "surprise": 1
    }
}