{
    "initial_scores": {
        "joy": 1,
        "sadness": 1,
        "fear": 1,
        "disgust": 1,
        "surprise": 1
    },
    "critique": "The document is a formal executive order regarding land use. It primarily deals with revoking and establishing land reservations for the Forest Service. There is no explicit emotional sentiment expressed. The language is legal and administrative, focusing on specific land descriptions and regulations. Therefore, all emotions should be scored low, with a default of 1 due to the lack of emotional content.",
    "revised_scores": {
        "joy": 1,
        "sadness": 1,
        "fear": 1,
        "disgust": 1,
        "surprise": 1
    }
}