{
    "initial_scores": {
        "joy": 2,
        "sadness": 1,
        "fear": 3,
        "disgust": 1,
        "surprise": 2
    },
    "critique": "The document is an executive order regarding the review process of decisions related to the Federal Aviation Act. The primary goal is to streamline the process and ensure national security and foreign policy considerations are taken into account. The tone is formal and bureaucratic. The language is precise and legalistic. The context is the President providing guidance to government agencies. The President likely wants to convey a sense of order, control, and efficiency. There is a desire to project an image of competence and seriousness. The document aims to instill confidence in the government's ability to handle complex issues related to aviation. The document does not explicitly aim to evoke strong emotions. However, the emphasis on national security might subtly aim to reduce fear and increase a sense of security. The focus on internal guidance and process suggests a desire to avoid surprise and maintain predictability. The revocation of a previous order suggests a desire for improvement and progress. Initial scores: Joy: 2, Sadness: 1, Anger: 1, Fear: 3, Disgust: 1, Surprise: 2 Revised scores: Joy: 3, Sadness: 1, Anger: 1, Fear: 2, Disgust: 1, Surprise: 1",
    "revised_scores": {
        "joy": 3,
        "sadness": 1,
        "fear": 2,
        "disgust": 1,
        "surprise": 1
    }
}