{
    "initial_scores": {
        "joy": 7,
        "sadness": 5,
        "fear": 4,
        "disgust": 3,
        "surprise": 2
    },
    "critique": "The document expresses a desire for peace, tranquility, and a beneficent government. This suggests the president wants to elicit joy and reduce sadness, fear, and disgust. There's a hint of surprise in the need for suggestions, but it's not a primary emotion. The initial scores reflect these considerations, but the revised scores adjust the intensity based on a more careful reading, emphasizing joy and reducing negative emotions.",
    "revised_scores": {
        "joy": 8,
        "sadness": 4,
        "fear": 3,
        "disgust": 2,
        "surprise": 1
    }
}