{
    "initial_scores": {
        "joy": 1,
        "sadness": 1,
        "fear": 2,
        "disgust": 1,
        "surprise": 1
    },
    "critique": "The document is a short executive order authorizing the Attorney General to make appointments without regard to civil service requirements. As the President, the primary emotion I want to elicit is a sense of confidence and decisive action during a time of potential crisis (given the date). There's not much emotional content here, but I'll try to infer based on the context and purpose. Initial assessment: Joy: 1 (not applicable), Sadness: 1 (not applicable), Fear: 2 (a slight sense of urgency), Disgust: 1 (not applicable), Surprise: 1 (not applicable), Anger: 1 (not applicable). Revised assessment: Upon further reflection, the order is more about efficiency and getting things done quickly. The emotions are still muted, but I would adjust the fear score slightly downward and perhaps add a touch of surprise that such an order is needed. Final scores: Joy: 1, Sadness: 1, Fear: 1, Disgust: 1, Surprise: 2, Anger: 1",
    "revised_scores": {
        "joy": 1,
        "sadness": 1,
        "fear": 1,
        "disgust": 1,
        "surprise": 2
    }
}