{
    "initial_scores": {
        "joy": 2,
        "sadness": 1,
        "fear": 1,
        "disgust": 1,
        "surprise": 2
    },
    "critique": "The document primarily conveys a sense of resolution and order. The tone is formal and administrative, focusing on the transfer of possession of a plant back to its original owner after it was used for war efforts. The primary emotion the President likely wants to elicit is a sense of stability and the smooth functioning of government processes during wartime. There's a subtle undercurrent of relief that the plant is no longer needed for war production, but it's not overtly expressed. Joy: 2 (slight relief), Sadness: 1 (no indication of sadness), Anger: 1 (no indication of anger), Fear: 1 (no indication of fear), Disgust: 1 (no indication of disgust), Surprise: 2 (a mild surprise that the plant is being relinquished). Revised scores: Joy: 3 (a bit more emphasis on the positive outcome), Sadness: 1, Anger: 1, Fear: 1, Disgust: 1, Surprise: 1 (less surprise, more expected).",
    "revised_scores": {
        "joy": 3,
        "sadness": 1,
        "fear": 1,
        "disgust": 1,
        "surprise": 1
    }
}