{
    "initial_scores": {
        "joy": 2,
        "sadness": 1,
        "fear": 1,
        "disgust": 1,
        "surprise": 1
    },
    "critique": "The document is primarily concerned with establishing regulations for additional compensation for US personnel working in foreign areas and territories with difficult living conditions, excessive hardship, or unhealthful conditions. The tone is formal and bureaucratic, focusing on definitions, eligibility, payment procedures, and periodic reviews. The primary emotion the President wants to elicit is a sense of fairness and order, ensuring that those serving in challenging environments are adequately compensated. There's also an element of practicality, aiming to incentivize recruitment and retention in these areas. There is little to suggest any strong emotions being conveyed. The document is very procedural and legalistic.",
    "revised_scores": {
        "joy": 2,
        "sadness": 1,
        "fear": 1,
        "disgust": 1,
        "surprise": 1
    }
}