{
    "initial_scores": {
        "joy": 4,
        "sadness": 1,
        "fear": 2,
        "disgust": 1,
        "surprise": 1
    },
    "critique": "The document is an executive order regarding a Code of Fair Competition for the Country Grain Elevator Industry. The tone is formal and legalistic. The primary goal is to establish and approve the code, suggesting a desire to convey a sense of order, progress, and stability. There's little explicit emotional expression, but the implicit emotions are related to confidence in the process and a hope for positive economic outcomes. Initial scores: Joy: 4 (sense of progress and positive economic outcomes), Sadness: 1 (no indication of sadness), Anger: 1 (no indication of anger), Fear: 2 (addressing potential economic instability), Disgust: 1 (no indication of disgust), Surprise: 1 (no indication of surprise). Revised scores: Joy: 5 (slight increase due to the approval), Sadness: 1, Anger: 1, Fear: 2, Disgust: 1, Surprise: 1.",
    "revised_scores": {
        "joy": 5,
        "sadness": 1,
        "fear": 2,
        "disgust": 1,
        "surprise": 1
    }
}