{
    "initial_scores": {
        "joy": 5,
        "sadness": 2,
        "fear": 3,
        "disgust": 3,
        "surprise": 4
    },
    "critique": "The document focuses on the legal and procedural aspects of enforcing Title VI of the Civil Rights Act. The tone is formal and authoritative, aiming to convey a sense of order and consistency in the government's approach to civil rights. The primary emotions the President likely wants to elicit are joy (through the promise of equal opportunity) and a reduction in fear and disgust (related to discrimination). There's also an element of surprise in revoking a previous executive order and centralizing authority under the Attorney General. The initial scores reflect this assessment, with joy being moderate, fear and disgust being low, and surprise being present. However, the initial scores might be overestimating the emotional impact. A more conservative revision is needed to reflect the document's primarily legal and administrative nature.",
    "revised_scores": {
        "joy": 4,
        "sadness": 1,
        "fear": 2,
        "disgust": 2,
        "surprise": 3
    }
}