{
    "initial_scores": {
        "joy": 2,
        "sadness": 1,
        "fear": 1,
        "disgust": 1,
        "surprise": 1
    },
    "critique": "The document is an executive order regarding the termination of the Petroleum Administration for War. As the President, the primary emotion I want to elicit is a sense of resolution and efficiency in winding down wartime agencies. The tone is formal and administrative, suggesting a desire for a smooth transition. There's no explicit emotional appeal, but the implicit message is one of competent governance. Initial scores: Joy: 2 (sense of resolution), Sadness: 1 (end of an era, but minimal), Anger: 1 (not applicable), Fear: 1 (not applicable), Disgust: 1 (not applicable), Surprise: 1 (not applicable). Revised scores: Joy: 3 (slightly increased for resolution), Sadness: 1, Anger: 1, Fear: 1, Disgust: 1, Surprise: 1.",
    "revised_scores": {
        "joy": 3,
        "sadness": 1,
        "fear": 1,
        "disgust": 1,
        "surprise": 1
    }
}