{
    "url": "https://www.presidency.ucsb.edu/documents/executive-order-6240-central-statistical-board",
    "doc": "executive-order-6240-central-statistical-board",
    "president": "Franklin D. Roosevelt",
    "president_byline": "32nd President of the United States: 1933 \u2010 1945",
    "title": "Executive Order 6240-Central Statistical Board",
    "date": "August 03, 1933",
    "content": [
        "I hereby designate Winfield W. Riefler as a member of the Central Statistical Board established by Executive Order Number 6225, dated July 27, 1933, and assign him as Economic Adviser to the Executive Council.",
        "FRANKLIN D. ROOSEVELT",
        "The White House,August 3, 1933."
    ],
    "citation": "Franklin D. Roosevelt, Executive Order 6240-Central Statistical Board Online by Gerhard Peters and John T. Woolley, The American Presidency Project https://www.presidency.ucsb.edu/node/362060"
}