{
    "initial_scores": {
        "ideological_tilt": 0,
        "immigration": 0,
        "executive_power": 0,
        "federalism": 0,
        "security_liberty": 0,
        "economic_regulation": 0,
        "social_inclusion": 0
    },
    "critique": "This executive order primarily deals with the transfer of authority and assets from the Office of Alien Property Custodian to the Attorney General. It's an internal government management issue with minimal direct impact on ideological tilt, immigration, federalism, security/liberties, economic regulation, or social inclusion. The use of the Trading with the Enemy Act and the First War Powers Act suggests a context related to wartime powers, but the order itself focuses on administrative transfer rather than expanding those powers. Therefore, most axes should be scored as neutral.",
    "revised_scores": {
        "ideological_tilt": 0,
        "immigration": 0,
        "executive_power": 0,
        "federalism": 0,
        "security_liberty": 0,
        "economic_regulation": 0,
        "social_inclusion": 0
    }
}