{
    "initial_scores": {
        "ideological_tilt": 0,
        "immigration": 0,
        "executive_power": 0,
        "federalism": 0,
        "security_liberty": 0,
        "economic_regulation": 0,
        "social_inclusion": 0
    },
    "critique": "The document expands executive power by suspending limitations on punishments for military offenses, potentially impacting individual liberties. It does not directly address economic regulation, social inclusion, immigration, or federalism. The ideological tilt is difficult to assess without more context, but the emphasis on military authority could be seen as leaning conservative.",
    "revised_scores": {
        "ideological_tilt": -1,
        "immigration": 0,
        "executive_power": 3,
        "federalism": 0,
        "security_liberty": 2,
        "economic_regulation": 0,
        "social_inclusion": 0
    }
}