{
    "initial_scores": {
        "ideological_tilt": 0,
        "immigration": 0,
        "executive_power": 0,
        "federalism": 0,
        "security_liberty": 0,
        "economic_regulation": 0,
        "social_inclusion": 0
    },
    "critique": "This document establishes a bird and wild animal refuge. It restricts hunting and destruction of natural resources within the area. It does not directly address ideological tilts, immigration, executive power, federalism, national security vs. civil liberties, economic regulation, or social inclusion. Therefore, most scores should be neutral.",
    "revised_scores": {
        "ideological_tilt": 0,
        "immigration": 0,
        "executive_power": 0,
        "federalism": 0,
        "security_liberty": 0,
        "economic_regulation": 0,
        "social_inclusion": 0
    }
}