{
    "initial_scores": {
        "ideological_tilt": 0,
        "immigration": 0,
        "executive_power": 0,
        "federalism": 0,
        "security_liberty": 0,
        "economic_regulation": 0,
        "social_inclusion": 0
    },
    "critique": "The document is a simple exemption from compulsory retirement for age for a government employee. It doesn't express strong opinions on any of the axes, but some can be inferred. It involves a government decision related to employment, which can be loosely tied to economic regulation. The decision is made by the executive branch, so it has implications for executive power. The document does not directly address social inclusion, immigration, federalism, security or liberty.",
    "revised_scores": {
        "ideological_tilt": 0,
        "immigration": 0,
        "executive_power": 1,
        "federalism": 0,
        "security_liberty": 0,
        "economic_regulation": 1,
        "social_inclusion": 0
    }
}