{
    "initial_scores": {
        "ideological_tilt": 0,
        "immigration": 0,
        "executive_power": 0,
        "federalism": 0,
        "security_liberty": 0,
        "economic_regulation": 0,
        "social_inclusion": 0
    },
    "critique": "This document pertains to the transfer of land between the US government and the Territory of Hawaii for an immigration station and harbor improvements. It outlines specific conditions for the transfer, including the construction of facilities and fences. There is minimal ideological content. Immigration is mentioned, but the document doesn't express an opinion on it. Executive power is used to facilitate the transfer, but it doesn't expand executive authority significantly. Federalism is relevant as it involves the relationship between the federal government and a territory, but the document seems neutral. National security vs. civil liberties is not a major theme. Economic regulation is not directly addressed. Social inclusion is not a prominent aspect.",
    "revised_scores": {
        "ideological_tilt": 0,
        "immigration": 0,
        "executive_power": 0,
        "federalism": 0,
        "security_liberty": 0,
        "economic_regulation": 0,
        "social_inclusion": 0
    }
}