{
    "initial_scores": {
        "ideological_tilt": 0,
        "immigration": 0,
        "executive_power": 0,
        "federalism": 0,
        "security_liberty": 0,
        "economic_regulation": 0,
        "social_inclusion": 0
    },
    "critique": "The document is an executive order regarding the payment of transportation expenses for government employees. It appears to be an administrative action with little to no impact on ideological tilt, immigration, executive power, federalism, security vs. liberty, economic regulation, or social inclusion. Therefore, the scores are set to neutral (0) across all axes.",
    "revised_scores": {
        "ideological_tilt": 0,
        "immigration": 0,
        "executive_power": 0,
        "federalism": 0,
        "security_liberty": 0,
        "economic_regulation": 0,
        "social_inclusion": 0
    }
}