{
    "initial_scores": {
        "ideological_tilt": 0,
        "immigration": 0,
        "executive_power": 0,
        "federalism": 0,
        "security_liberty": 0,
        "economic_regulation": 3,
        "social_inclusion": 0
    },
    "critique": "This document pertains to trade regulations between the US and Canada regarding red cedar shingles. It sets import quotas based on a reciprocal trade agreement. There's no direct indication of ideological leaning, immigration policy, or civil liberties concerns. The executive power is being used to implement a trade agreement, which is a fairly standard function. Federalism isn't strongly affected. Economic regulation is present in the form of import quotas. Social inclusion is not relevant to this document.\n\nInitial scores:\n* Ideological Tilt: 0 (Centrist/Moderate)\n* Immigration Approach: 0 (Balanced/Selective) - although it deals with imports, not people\n* Executive Power: 0 (Neutral/Balanced)\n* Federalism: 0 (Cooperative Balance)\n* National Security vs. Civil Liberties: 0 (Balanced Approach)\n* Economic Regulation: 3 (Moderate Government Intervention)\n* Social Inclusion: 0 (Neutral)\n\nRevised scores:\n* Ideological Tilt: 0 (Centrist/Moderate)\n* Immigration Approach: 0 (Balanced/Selective)\n* Executive Power: 0 (Neutral/Balanced)\n* Federalism: 0 (Cooperative Balance)\n* National Security vs. Civil Liberties: 0 (Balanced Approach)\n* Economic Regulation: 3 (Moderate Government Intervention)\n* Social Inclusion: 0 (Neutral)",
    "revised_scores": {
        "ideological_tilt": 0,
        "immigration": 0,
        "executive_power": 0,
        "federalism": 0,
        "security_liberty": 0,
        "economic_regulation": 3,
        "social_inclusion": 0
    }
}