{
    "initial_scores": {
        "ideological_tilt": 1,
        "immigration": -2,
        "executive_power": 3,
        "federalism": 0,
        "security_liberty": 2,
        "economic_regulation": 0,
        "social_inclusion": 1
    },
    "critique": "The document is an executive order issued by President Obama concerning the situation in South Sudan. It declares a national emergency and imposes sanctions on individuals and entities involved in activities that threaten the peace, security, or stability of South Sudan. The order also suspends the entry of such persons into the United States.",
    "revised_scores": {
        "ideological_tilt": 1,
        "immigration": -2,
        "executive_power": 3,
        "federalism": 0,
        "security_liberty": 2,
        "economic_regulation": 0,
        "social_inclusion": 1
    }
}