{
    "initial_scores": {
        "ideological_tilt": 0,
        "immigration": 0,
        "executive_power": 5,
        "federalism": 0,
        "security_liberty": 0,
        "economic_regulation": 0,
        "social_inclusion": 0
    },
    "critique": "The document is a waiver related to trade with China, focusing on executive authority in foreign policy. It doesn't directly address social issues, economic regulation, or domestic policy, making it difficult to assess ideological tilt or social inclusion. The primary focus is on the President's power to waive trade restrictions.",
    "revised_scores": {
        "ideological_tilt": 0,
        "immigration": 0,
        "executive_power": 5,
        "federalism": 0,
        "security_liberty": 0,
        "economic_regulation": 0,
        "social_inclusion": 0
    }
}