{
    "initial_scores": {
        "ideological_tilt": 0,
        "immigration": 0,
        "executive_power": 0,
        "federalism": 0,
        "security_liberty": 0,
        "economic_regulation": 0,
        "social_inclusion": 0
    },
    "critique": "The document delegates presidential powers to the Secretary of War, the Under Secretary of War, the Secretary of the Navy and the Under Secretary of the Navy. It does not touch upon economic regulation, immigration, social inclusion, or ideological tilt. The document seems to expand executive power during war.",
    "revised_scores": {
        "ideological_tilt": 0,
        "immigration": 0,
        "executive_power": 3,
        "federalism": 0,
        "security_liberty": 2,
        "economic_regulation": 0,
        "social_inclusion": 0
    }
}