{
    "initial_scores": {
        "ideological_tilt": 0,
        "immigration": 0,
        "executive_power": 0,
        "federalism": 2,
        "security_liberty": 0,
        "economic_regulation": 1,
        "social_inclusion": 0
    },
    "critique": "The document emphasizes reducing unfunded mandates and increasing flexibility for state, local, and tribal governments, suggesting a preference for decentralized governance and less federal intervention. It also aims to streamline waiver processes, indicating a desire to reduce regulatory burdens. The document does not directly address immigration, security, or social inclusion. The order is intended to improve internal management and does not create enforceable rights.",
    "revised_scores": {
        "ideological_tilt": -1,
        "immigration": 0,
        "executive_power": -1,
        "federalism": -2,
        "security_liberty": 0,
        "economic_regulation": -1,
        "social_inclusion": 0
    }
}