{
    "initial_scores": {
        "ideological_tilt": -1,
        "immigration": 0,
        "executive_power": 1,
        "federalism": 4,
        "security_liberty": 2,
        "economic_regulation": 0,
        "social_inclusion": 0
    },
    "critique": "This document concerns the administration of the Philippines in 1916. Given the historical context, it's difficult to apply modern political axes directly. However, we can make some inferences:\n\n*   **Ideological Tilt:** The document itself is neutral, simply outlining administrative procedures. However, the act it references aims to provide a more autonomous government, which could be seen as a slightly liberal approach for the time, but not strongly so. I will score it as slightly conservative due to the time period.\n*   **Immigration Approach:** Irrelevant to this document.\n*   **Executive Power:** The document delegates additional duties to the Governor General by the President, suggesting a slight expansion of executive power.\n*   **Federalism:** This is about the relationship between the US federal government and the Philippines, which is not a US state. The document centralizes control in the War Department, indicating strong federal control over the Philippines.\n*   **National Security vs. Civil Liberties:** The document doesn't directly address this, but placing the administration under the War Department suggests a prioritization of security or control.\n*   **Economic Regulation:** Irrelevant to this document.\n*   **Social Inclusion:** Irrelevant to this document.\n\nRevised Scores: After further consideration, the initial scores seem reasonable given the context. The document reflects the colonial administration of the time, with a focus on federal control and security. The slight expansion of executive power and the conservative tilt are also appropriate interpretations.",
    "revised_scores": {
        "ideological_tilt": -1,
        "immigration": 0,
        "executive_power": 1,
        "federalism": 4,
        "security_liberty": 2,
        "economic_regulation": 0,
        "social_inclusion": 0
    }
}