{
    "initial_scores": {
        "ideological_tilt": 0,
        "immigration": 0,
        "executive_power": 1,
        "federalism": 1,
        "security_liberty": 0,
        "economic_regulation": 1,
        "social_inclusion": 0
    },
    "critique": "This document establishes the Office of Administration within the Executive Office of the President. It centralizes administrative support and services for various units within the EOP. It doesn't directly address ideological issues, immigration, or civil liberties. The order seems primarily focused on improving efficiency and streamlining administrative functions within the executive branch. There's a slight expansion of executive power through centralization, and a move towards federal primacy by consolidating administrative functions. There's a moderate level of economic intervention through centralized services, and a neutral stance on social inclusion.",
    "revised_scores": {
        "ideological_tilt": 0,
        "immigration": 0,
        "executive_power": 1,
        "federalism": 1,
        "security_liberty": 0,
        "economic_regulation": 1,
        "social_inclusion": 0
    }
}