{
    "initial_scores": {
        "ideological_tilt": 0,
        "immigration": 0,
        "executive_power": 0,
        "federalism": 0,
        "security_liberty": 0,
        "economic_regulation": 0,
        "social_inclusion": -1
    },
    "critique": "This document pertains to the suspension of certain provisions related to officer promotions within specific branches of the US Navy during a national emergency. It appears to temporarily modify existing regulations concerning selection boards and promotion criteria, specifically referencing sections of Title 10 of the United States Code. There is a mention of gender with regards to women officers appointed under section 5590. The document does not seem to directly address ideological issues, immigration, executive power, federalism, national security vs. civil liberties, economic regulation, or broad social inclusion policies. The document seems to be gendered in its language.",
    "revised_scores": {
        "ideological_tilt": 0,
        "immigration": 0,
        "executive_power": 0,
        "federalism": 0,
        "security_liberty": 0,
        "economic_regulation": 0,
        "social_inclusion": -1
    }
}