{
    "initial_scores": {
        "ideological_tilt": 0,
        "immigration": 0,
        "executive_power": 2,
        "federalism": 3,
        "security_liberty": 0,
        "economic_regulation": 3,
        "social_inclusion": 0
    },
    "critique": "The document extends the Federal Aviation Act to the Ryukyu Islands, granting the Civil Aeronautics Board and the High Commissioner certain regulatory powers. It centralizes control over aviation, balancing federal oversight with local administration by the High Commissioner. There is no mentioning of immigration, civil liberties, or social issues.",
    "revised_scores": {
        "ideological_tilt": 0,
        "immigration": 0,
        "executive_power": 2,
        "federalism": 3,
        "security_liberty": 0,
        "economic_regulation": 3,
        "social_inclusion": 0
    }
}