{
    "initial_scores": {
        "ideological_tilt": 1,
        "immigration": 0,
        "executive_power": 1,
        "federalism": 2,
        "security_liberty": 0,
        "economic_regulation": 2,
        "social_inclusion": 1
    },
    "critique": "The document focuses on establishing a national health information technology infrastructure. It emphasizes interoperability, quality improvement, and efficiency in healthcare through technology. There's a clear delegation of authority to the Secretary of Health and Human Services and the National Health Information Technology Coordinator. The document seeks to balance public and private interests and improve healthcare outcomes through technological advancements.",
    "revised_scores": {
        "ideological_tilt": 1,
        "immigration": 0,
        "executive_power": 2,
        "federalism": 3,
        "security_liberty": 1,
        "economic_regulation": 3,
        "social_inclusion": 1
    }
}