{
    "initial_scores": {
        "ideological_tilt": 2,
        "immigration": 0,
        "executive_power": 4,
        "federalism": 4,
        "security_liberty": 3,
        "economic_regulation": 3,
        "social_inclusion": 0
    },
    "critique": "This document is an executive order from 1942 related to the Second War Powers Act. It authorizes the Federal Works Administrator to acquire property for war purposes. Given the context of World War II, several biases are apparent. Ideologically, it reflects a strong national unity and purpose, which doesn't neatly fit on a left-right spectrum but leans towards a collective, interventionist approach. Immigration is not directly addressed. Executive power is expanded to facilitate war efforts. Federalism is strengthened as the federal government takes control of resources. National security is prioritized over individual liberties in this time of war. Economic regulation is increased to support the war effort. Social inclusion is not a primary focus, but the war effort likely demanded a degree of social cohesion.",
    "revised_scores": {
        "ideological_tilt": 2,
        "immigration": 0,
        "executive_power": 4,
        "federalism": 4,
        "security_liberty": 4,
        "economic_regulation": 4,
        "social_inclusion": 0
    }
}